[{"trends":[{"name":"Singapore","url":"http://twitter.com/search?q=Singapore","promoted_content":null,"query":"Singapore","tweet_volume":181005},{"name":"#ThePeopleChooseBTS","url":"http://twitter.com/search?q=%23ThePeopleChooseBTS","promoted_content":null,"query":"%23ThePeopleChooseBTS","tweet_volume":450656},{"name":"#모든_것을_이겨라","url":"http://twitter.com/search?q=%23%EB%AA%A8%EB%93%A0_%EA%B2%83%EC%9D%84_%EC%9D%B4%EA%B2%A8%EB%9D%BC","promoted_content":null,"query":"%23%EB%AA%A8%EB%93%A0_%EA%B2%83%EC%9D%84_%EC%9D%B4%EA%B2%A8%EB%9D%BC","tweet_volume":106607},{"name":"#SFFxSWITCH","url":"http://twitter.com/search?q=%23SFFxSWITCH","promoted_content":null,"query":"%23SFFxSWITCH","tweet_volume":null},{"name":"#LightUpX1","url":"http://twitter.com/search?q=%23LightUpX1","promoted_content":null,"query":"%23LightUpX1","tweet_volume":173296},{"name":"#EXplOrationInMY","url":"http://twitter.com/search?q=%23EXplOrationInMY","promoted_content":null,"query":"%23EXplOrationInMY","tweet_volume":null},{"name":"Liverpool","url":"http://twitter.com/search?q=Liverpool","promoted_content":null,"query":"Liverpool","tweet_volume":453127},{"name":"man city","url":"http://twitter.com/search?q=%22man+city%22","promoted_content":null,"query":"%22man+city%22","tweet_volume":97419},{"name":"Arashi","url":"http://twitter.com/search?q=Arashi","promoted_content":null,"query":"Arashi","tweet_volume":253627},{"name":"Anfield","url":"http://twitter.com/search?q=Anfield","promoted_content":null,"query":"Anfield","tweet_volume":107257},{"name":"Mane","url":"http://twitter.com/search?q=Mane","promoted_content":null,"query":"Mane","tweet_volume":103856},{"name":"Sterling","url":"http://twitter.com/search?q=Sterling","promoted_content":null,"query":"Sterling","tweet_volume":65898},{"name":"Shiv Sena","url":"http://twitter.com/search?q=%22Shiv+Sena%22","promoted_content":null,"query":"%22Shiv+Sena%22","tweet_volume":73735},{"name":"Fabinho","url":"http://twitter.com/search?q=Fabinho","promoted_content":null,"query":"Fabinho","tweet_volume":71668},{"name":"Rashford","url":"http://twitter.com/search?q=Rashford","promoted_content":null,"query":"Rashford","tweet_volume":57352},{"name":"Brandon Williams","url":"http://twitter.com/search?q=%22Brandon+Williams%22","promoted_content":null,"query":"%22Brandon+Williams%22","tweet_volume":18779},{"name":"Lazada","url":"http://twitter.com/search?q=Lazada","promoted_content":null,"query":"Lazada","tweet_volume":113696},{"name":"logan paul","url":"http://twitter.com/search?q=%22logan+paul%22","promoted_content":null,"query":"%22logan+paul%22","tweet_volume":122568},{"name":"suju","url":"http://twitter.com/search?q=suju","promoted_content":null,"query":"suju","tweet_volume":31334},{"name":"klopp","url":"http://twitter.com/search?q=klopp","promoted_content":null,"query":"klopp","tweet_volume":70884},{"name":"#TomorrowWithIZONE","url":"http://twitter.com/search?q=%23TomorrowWithIZONE","promoted_content":null,"query":"%23TomorrowWithIZONE","tweet_volume":88312},{"name":"#LIVMCI","url":"http://twitter.com/search?q=%23LIVMCI","promoted_content":null,"query":"%23LIVMCI","tweet_volume":270419},{"name":"#ObsessedWithKAI","url":"http://twitter.com/search?q=%23ObsessedWithKAI","promoted_content":null,"query":"%23ObsessedWithKAI","tweet_volume":516965},{"name":"#KAMPinSG","url":"http://twitter.com/search?q=%23KAMPinSG","promoted_content":null,"query":"%23KAMPinSG","tweet_volume":15953},{"name":"#SUPERJUNIOR","url":"http://twitter.com/search?q=%23SUPERJUNIOR","promoted_content":null,"query":"%23SUPERJUNIOR","tweet_volume":112641},{"name":"#ForWonho","url":"http://twitter.com/search?q=%23ForWonho","promoted_content":null,"query":"%23ForWonho","tweet_volume":470776},{"name":"#Worlds2019","url":"http://twitter.com/search?q=%23Worlds2019","promoted_content":null,"query":"%23Worlds2019","tweet_volume":226675},{"name":"#ForMonstaX7","url":"http://twitter.com/search?q=%23ForMonstaX7","promoted_content":null,"query":"%23ForMonstaX7","tweet_volume":607405},{"name":"#ynwa","url":"http://twitter.com/search?q=%23ynwa","promoted_content":null,"query":"%23ynwa","tweet_volume":52009},{"name":"#변화를_위해_싸우다","url":"http://twitter.com/search?q=%23%EB%B3%80%ED%99%94%EB%A5%BC_%EC%9C%84%ED%95%B4_%EC%8B%B8%EC%9A%B0%EB%8B%A4","promoted_content":null,"query":"%23%EB%B3%80%ED%99%94%EB%A5%BC_%EC%9C%84%ED%95%B4_%EC%8B%B8%EC%9A%B0%EB%8B%A4","tweet_volume":392635},{"name":"#kaivskāi","url":"http://twitter.com/search?q=%23kaivsk%C4%81i","promoted_content":null,"query":"%23kaivsk%C4%81i","tweet_volume":239622},{"name":"#wjsn","url":"http://twitter.com/search?q=%23wjsn","promoted_content":null,"query":"%23wjsn","tweet_volume":31218},{"name":"#teamksi","url":"http://twitter.com/search?q=%23teamksi","promoted_content":null,"query":"%23teamksi","tweet_volume":23223},{"name":"#taeyong","url":"http://twitter.com/search?q=%23taeyong","promoted_content":null,"query":"%23taeyong","tweet_volume":101878},{"name":"#SinglesDay","url":"http://twitter.com/search?q=%23SinglesDay","promoted_content":null,"query":"%23SinglesDay","tweet_volume":null},{"name":"#hcaasia2019","url":"http://twitter.com/search?q=%23hcaasia2019","promoted_content":null,"query":"%23hcaasia2019","tweet_volume":null},{"name":"#JETSTORM","url":"http://twitter.com/search?q=%23JETSTORM","promoted_content":null,"query":"%23JETSTORM","tweet_volume":80625},{"name":"#Siwon","url":"http://twitter.com/search?q=%23Siwon","promoted_content":null,"query":"%23Siwon","tweet_volume":13809},{"name":"#nct127","url":"http://twitter.com/search?q=%23nct127","promoted_content":null,"query":"%23nct127","tweet_volume":256443},{"name":"#스트레이키즈","url":"http://twitter.com/search?q=%23%EC%8A%A4%ED%8A%B8%EB%A0%88%EC%9D%B4%ED%82%A4%EC%A6%88","promoted_content":null,"query":"%23%EC%8A%A4%ED%8A%B8%EB%A0%88%EC%9D%B4%ED%82%A4%EC%A6%88","tweet_volume":286310},{"name":"#WangYibo","url":"http://twitter.com/search?q=%23WangYibo","promoted_content":null,"query":"%23WangYibo","tweet_volume":269194},{"name":"#momoland","url":"http://twitter.com/search?q=%23momoland","promoted_content":null,"query":"%23momoland","tweet_volume":11123},{"name":"#gouste","url":"http://twitter.com/search?q=%23gouste","promoted_content":null,"query":"%23gouste","tweet_volume":12191},{"name":"#CAFEVMIN","url":"http://twitter.com/search?q=%23CAFEVMIN","promoted_content":null,"query":"%23CAFEVMIN","tweet_volume":null},{"name":"#kyuhyun","url":"http://twitter.com/search?q=%23kyuhyun","promoted_content":null,"query":"%23kyuhyun","tweet_volume":30461},{"name":"#ksivsloganpaul2","url":"http://twitter.com/search?q=%23ksivsloganpaul2","promoted_content":null,"query":"%23ksivsloganpaul2","tweet_volume":76261},{"name":"#hasungwoon","url":"http://twitter.com/search?q=%23hasungwoon","promoted_content":null,"query":"%23hasungwoon","tweet_volume":52179},{"name":"#felix","url":"http://twitter.com/search?q=%23felix","promoted_content":null,"query":"%23felix","tweet_volume":33583},{"name":"#emeryout","url":"http://twitter.com/search?q=%23emeryout","promoted_content":null,"query":"%23emeryout","tweet_volume":10780},{"name":"#mufc","url":"http://twitter.com/search?q=%23mufc","promoted_content":null,"query":"%23mufc","tweet_volume":81943}],"as_of":"2019-11-11T05:52:45Z","created_at":"2019-11-11T05:45:53Z","locations":[{"name":"Singapore","woeid":1062617}]}]
